pylicense/__init__.py
pylicense/cli.py
pylicense/constants.py
pylicense/dispatcher.py
pylicense/logger.py
pylicense/parser.py
pylicense/repos/__init__.py
pylicense/repos/anaconda.py
pylicense/repos/base.py
pylicense/repos/conda_forge.py
pylicense/repos/pypi.py
dcs_pylicense-0.0.3.dist-info/LICENSE
dcs_pylicense-0.0.3.dist-info/METADATA
dcs_pylicense-0.0.3.dist-info/WHEEL
dcs_pylicense-0.0.3.dist-info/entry_points.txt
dcs_pylicense-0.0.3.dist-info/top_level.txt
dcs_pylicense-0.0.3.dist-info/RECORD
