Metadata-Version: 2.1
Name: dcs-pylicense
Version: 0.0.3
Summary: PyLicense is a CLI tool that queries license information from one of the following package repositories: PyPI, Anaconda or conda-forge.
Home-page: https://github.com/dotcs/pylicense
Author: Fabian Mueller
Author-email: repository@dotcs.me
License: GPLv3
Platform: UNKNOWN
Classifier: Development Status :: 3 - Alpha
Classifier: Environment :: Console
Classifier: License :: OSI Approved :: GNU General Public License v3 (GPLv3)
Classifier: Natural Language :: English
Classifier: Operating System :: OS Independent
Classifier: Programming Language :: Python :: 3
Classifier: Topic :: Office/Business
Requires-Python: >=3.6
Requires-Dist: beautifulsoup4
Requires-Dist: requests
Requires-Dist: pandas
Requires-Dist: tabulate
Provides-Extra: develop
Requires-Dist: black ; extra == 'develop'
Requires-Dist: pylint ; extra == 'develop'
Requires-Dist: pytest ; extra == 'develop'
Requires-Dist: pytest-cov ; extra == 'develop'
Requires-Dist: sphinx (<4,>=3.2.1) ; extra == 'develop'
Requires-Dist: twine ; extra == 'develop'
